MANIFEST.in
README.rst
setup.py
wlnm/__init__.py
wlnm/agent.py
wlnm/daemon.py
wlnm/database.py
wlnm/inputer.py
wlnm/monitor.py
wlnm/search.py
wlnm/server.py
wlnm/starter.py
wlnm/test.py
wlnm/util.py
wlnm/webserver.py
wlnm/wlna.py
wlnm/wlnac.py
wlnm/wlnad.py
wlnm/wlnm.py
wlnm/wlns.py
wlnm/wlnsc.py
wlnm/wlnsd.py
wlnm/wlnws.py
wlnm/wls.py
wlnm.egg-info/PKG-INFO
wlnm.egg-info/SOURCES.txt
wlnm.egg-info/dependency_links.txt
wlnm.egg-info/entry_points.txt
wlnm.egg-info/requires.txt
wlnm.egg-info/top_level.txt
wlnm/app/404.html
wlnm/app/__init__.py
wlnm/app/favicon.ico
wlnm/app/index.html
wlnm/app/css/__init__.py
wlnm/app/css/app.css
wlnm/app/js/__init__.py
wlnm/app/js/app.js
wlnm/app/js/controllers.js
wlnm/app/js/directives.js
wlnm/app/js/filters.js
wlnm/app/js/services.js
wlnm/app/lib/__init__.py
wlnm/app/lib/angular/angular-cookies.js
wlnm/app/lib/angular/angular-cookies.min.js
wlnm/app/lib/angular/angular-loader.js
wlnm/app/lib/angular/angular-loader.min.js
wlnm/app/lib/angular/angular-resource.js
wlnm/app/lib/angular/angular-resource.min.js
wlnm/app/lib/angular/angular-sanitize.js
wlnm/app/lib/angular/angular-sanitize.min.js
wlnm/app/lib/angular/angular.js
wlnm/app/lib/angular/angular.min.js
wlnm/app/lib/angular/version.txt
wlnm/app/templates/__init__.py
wlnm/app/templates/main.html
wlnm/wlst/__init__.py
wlnm/wlst/decryptPass.py
wlnm/wlst/startwls.py
wlnm/wlst/stopwls.py