Metadata-Version: 1.0
Name: wlnm
Version: 1.0.1
Summary: Weblogic Node Master
Home-page: https://github.com/yikaus/wlnm
Author: Kevin Yi
Author-email: yikaus A gmail 
License: BSD
Keywords: weblogic admin administrator node manage
Platform: UNKNOWN
